{"type": "FeatureCollection", "features": [{"type": "Feature", "properties": {"name_zh": "Fiji", "tier": 3, "min_zoom": 4, "orig_lng": 179.399519875}, "geometry": {"type": "Point", "coordinates": [179.399519875, -16.494383374999998]}}, {"type": "Feature", "properties": {"name_zh": "Tanzania", "tier": 2, "min_zoom": 3, "orig_lng": 34.31407998076923}, "geometry": {"type": "Point", "coordinates": [34.31407998076923, -6.544286499999999]}}, {"type": "Feature", "properties": {"name_zh": "W. Sahara", "tier": 3, "min_zoom": 4, "orig_lng": -12.027395285714286}, "geometry": {"type": "Point", "coordinates": [-12.027395285714286, 24.777708071428574]}}, {"type": "Feature", "properties": {"name_zh": "加拿大", "tier": 1, "min_zoom": 2, "orig_lng": -91.07149176642336}, "geometry": {"type": "Point", "coordinates": [-91.07149176642336, 56.44521802189781]}}, {"type": "Feature", "properties": {"name_zh": "United States of America", "tier": 1, "min_zoom": 2, "orig_lng": -90.36496205150215}, "geometry": {"type": "Point", "coordinates": [-90.36496205150215, 38.27425020171674]}}, {"type": "Feature", "properties": {"name_zh": "Kazakhstan", "tier": 1, "min_zoom": 2, "orig_lng": 65.25235867857143}, "geometry": {"type": "Point", "coordinates": [65.25235867857143, 47.26379638392857]}}, {"type": "Feature", "properties": {"name_zh": "Uzbekistan", "tier": 2, "min_zoom": 3, "orig_lng": 65.28922640740741}, "geometry": {"type": "Point", "coordinates": [65.28922640740741, 41.152646796296295]}}, {"type": "Feature", "properties": {"name_zh": "Papua New Guinea", "tier": 2, "min_zoom": 3, "orig_lng": 146.21341852941177}, "geometry": {"type": "Point", "coordinates": [146.21341852941177, -7.771741529411765]}}, {"type": "Feature", "properties": {"name_zh": "印度尼西亚", "tier": 1, "min_zoom": 2, "orig_lng": 135.81676642105265}, "geometry": {"type": "Point", "coordinates": [135.81676642105265, -3.766696210526316]}}, {"type": "Feature", "properties": {"name_zh": "阿根廷", "tier": 1, "min_zoom": 2, "orig_lng": -67.26124818181819}, "geometry": {"type": "Point", "coordinates": [-67.26124818181819, -54.22355090909091]}}, {"type": "Feature", "properties": {"name_zh": "Chile", "tier": 2, "min_zoom": 3, "orig_lng": -70.12479005}, "geometry": {"type": "Point", "coordinates": [-70.12479005, -54.16730690000001]}}, {"type": "Feature", "properties": {"name_zh": "Dem. Rep. Congo", "tier": 3, "min_zoom": 4, "orig_lng": 23.126932951612904}, "geometry": {"type": "Point", "coordinates": [23.126932951612904, -3.813813258064516]}}, {"type": "Feature", "properties": {"name_zh": "Somalia", "tier": 2, "min_zoom": 3, "orig_lng": 46.897339945945944}, "geometry": {"type": "Point", "coordinates": [46.897339945945944, 6.553593081081081]}}, {"type": "Feature", "properties": {"name_zh": "肯尼亚", "tier": 2, "min_zoom": 3, "orig_lng": 37.823721432432436}, "geometry": {"type": "Point", "coordinates": [37.823721432432436, 1.1144695945945946]}}, {"type": "Feature", "properties": {"name_zh": "苏丹", "tier": 1, "min_zoom": 2, "orig_lng": 29.337440839506172}, "geometry": {"type": "Point", "coordinates": [29.337440839506172, 12.80797675308642]}}, {"type": "Feature", "properties": {"name_zh": "Chad", "tier": 2, "min_zoom": 3, "orig_lng": 17.995556810344826}, "geometry": {"type": "Point", "coordinates": [17.995556810344826, 12.995734793103448]}}, {"type": "Feature", "properties": {"name_zh": "Haiti", "tier": 3, "min_zoom": 4, "orig_lng": -72.70254709523809}, "geometry": {"type": "Point", "coordinates": [-72.70254709523809, 18.839613285714286]}}, {"type": "Feature", "properties": {"name_zh": "Dominican Rep.", "tier": 3, "min_zoom": 4, "orig_lng": -70.4934206923077}, "geometry": {"type": "Point", "coordinates": [-70.4934206923077, 18.725987076923076]}}, {"type": "Feature", "properties": {"name_zh": "俄罗斯", "tier": 1, "min_zoom": 2, "orig_lng": 179.27080500000002}, "geometry": {"type": "Point", "coordinates": [179.27080500000002, 71.0653306]}}, {"type": "Feature", "properties": {"name_zh": "Bahamas", "tier": 3, "min_zoom": 4, "orig_lng": -78.50833333333334}, "geometry": {"type": "Point", "coordinates": [-78.50833333333334, 26.715]}}, {"type": "Feature", "properties": {"name_zh": "Falkland Is.", "tier": 3, "min_zoom": 4, "orig_lng": -59.585}, "geometry": {"type": "Point", "coordinates": [-59.585, -51.735]}}, {"type": "Feature", "properties": {"name_zh": "挪威", "tier": 2, "min_zoom": 3, "orig_lng": 15.604357222222221}, "geometry": {"type": "Point", "coordinates": [15.604357222222221, 78.72300000000001]}}, {"type": "Feature", "properties": {"name_zh": "Greenland", "tier": 1, "min_zoom": 2, "orig_lng": -41.03145590909091}, "geometry": {"type": "Point", "coordinates": [-41.03145590909091, 74.14763175757577]}}, {"type": "Feature", "properties": {"name_zh": "Fr. S. Antarctic Lands", "tier": 3, "min_zoom": 4, "orig_lng": 69.46083333333334}, "geometry": {"type": "Point", "coordinates": [69.46083333333334, -49.11861111111111]}}, {"type": "Feature", "properties": {"name_zh": "Timor-Leste", "tier": 3, "min_zoom": 4, "orig_lng": 125.90554309090909}, "geometry": {"type": "Point", "coordinates": [125.90554309090909, -8.74553581818182]}}, {"type": "Feature", "properties": {"name_zh": "南非", "tier": 1, "min_zoom": 2, "orig_lng": 24.719575}, "geometry": {"type": "Point", "coordinates": [24.719575, -28.603900060975608]}}, {"type": "Feature", "properties": {"name_zh": "Lesotho", "tier": 3, "min_zoom": 4, "orig_lng": 28.370332416666667}, "geometry": {"type": "Point", "coordinates": [28.370332416666667, -29.584757416666665]}}, {"type": "Feature", "properties": {"name_zh": "墨西哥", "tier": 1, "min_zoom": 2, "orig_lng": -103.1307627235294}, "geometry": {"type": "Point", "coordinates": [-103.1307627235294, 23.874573264705884]}}, {"type": "Feature", "properties": {"name_zh": "Uruguay", "tier": 2, "min_zoom": 3, "orig_lng": -56.138627666666665}, "geometry": {"type": "Point", "coordinates": [-56.138627666666665, -32.69753633333333]}}, {"type": "Feature", "properties": {"name_zh": "巴西", "tier": 1, "min_zoom": 2, "orig_lng": -56.92618139901478}, "geometry": {"type": "Point", "coordinates": [-56.92618139901478, -9.65648730049261]}}, {"type": "Feature", "properties": {"name_zh": "Bolivia", "tier": 2, "min_zoom": 3, "orig_lng": -64.13008903333333}, "geometry": {"type": "Point", "coordinates": [-64.13008903333333, -16.336588166666665]}}, {"type": "Feature", "properties": {"name_zh": "Peru", "tier": 2, "min_zoom": 3, "orig_lng": -74.08178505263159}, "geometry": {"type": "Point", "coordinates": [-74.08178505263159, -7.7531079736842115]}}, {"type": "Feature", "properties": {"name_zh": "Colombia", "tier": 2, "min_zoom": 3, "orig_lng": -72.65296166}, "geometry": {"type": "Point", "coordinates": [-72.65296166, 4.490703470000001]}}, {"type": "Feature", "properties": {"name_zh": "Panama", "tier": 3, "min_zoom": 4, "orig_lng": -80.31720192307692}, "geometry": {"type": "Point", "coordinates": [-80.31720192307692, 8.495830826923077]}}, {"type": "Feature", "properties": {"name_zh": "Costa Rica", "tier": 3, "min_zoom": 4, "orig_lng": -84.16182833333333}, "geometry": {"type": "Point", "coordinates": [-84.16182833333333, 9.822146222222223]}}, {"type": "Feature", "properties": {"name_zh": "Nicaragua", "tier": 3, "min_zoom": 4, "orig_lng": -84.97791375}, "geometry": {"type": "Point", "coordinates": [-84.97791375, 13.07882925]}}, {"type": "Feature", "properties": {"name_zh": "Honduras", "tier": 3, "min_zoom": 4, "orig_lng": -86.30799807017543}, "geometry": {"type": "Point", "coordinates": [-86.30799807017543, 14.746302210526316]}}, {"type": "Feature", "properties": {"name_zh": "El Salvador", "tier": 3, "min_zoom": 4, "orig_lng": -88.9199223}, "geometry": {"type": "Point", "coordinates": [-88.9199223, 13.854635300000002]}}, {"type": "Feature", "properties": {"name_zh": "Guatemala", "tier": 3, "min_zoom": 4, "orig_lng": -90.26977582857143}, "geometry": {"type": "Point", "coordinates": [-90.26977582857143, 15.531142428571428]}}, {"type": "Feature", "properties": {"name_zh": "Belize", "tier": 3, "min_zoom": 4, "orig_lng": -88.63038305}, "geometry": {"type": "Point", "coordinates": [-88.63038305, 17.4171646]}}, {"type": "Feature", "properties": {"name_zh": "Venezuela", "tier": 2, "min_zoom": 3, "orig_lng": -66.85159614130434}, "geometry": {"type": "Point", "coordinates": [-66.85159614130434, 7.213489043478261]}}, {"type": "Feature", "properties": {"name_zh": "Guyana", "tier": 3, "min_zoom": 4, "orig_lng": -58.89834125}, "geometry": {"type": "Point", "coordinates": [-58.89834125, 4.481521375]}}, {"type": "Feature", "properties": {"name_zh": "Suriname", "tier": 3, "min_zoom": 4, "orig_lng": -55.87038857692308}, "geometry": {"type": "Point", "coordinates": [-55.87038857692308, 3.6974153076923075]}}, {"type": "Feature", "properties": {"name_zh": "法国", "tier": 1, "min_zoom": 2, "orig_lng": -53.37074605263158}, "geometry": {"type": "Point", "coordinates": [-53.37074605263158, 3.547146789473685]}}, {"type": "Feature", "properties": {"name_zh": "Ecuador", "tier": 2, "min_zoom": 3, "orig_lng": -78.70452248484848}, "geometry": {"type": "Point", "coordinates": [-78.70452248484848, -1.637014393939394]}}, {"type": "Feature", "properties": {"name_zh": "Puerto Rico", "tier": 3, "min_zoom": 4, "orig_lng": -66.43350466666668}, "geometry": {"type": "Point", "coordinates": [-66.43350466666668, 18.275953444444443]}}, {"type": "Feature", "properties": {"name_zh": "Jamaica", "tier": 3, "min_zoom": 4, "orig_lng": -77.34805227272727}, "geometry": {"type": "Point", "coordinates": [-77.34805227272727, 18.187741363636363]}}, {"type": "Feature", "properties": {"name_zh": "Cuba", "tier": 3, "min_zoom": 4, "orig_lng": -79.73309490476191}, "geometry": {"type": "Point", "coordinates": [-79.73309490476191, 21.722816714285713]}}, {"type": "Feature", "properties": {"name_zh": "津巴布韦", "tier": 2, "min_zoom": 3, "orig_lng": 29.658726567567566}, "geometry": {"type": "Point", "coordinates": [29.658726567567566, -18.870223]}}, {"type": "Feature", "properties": {"name_zh": "Botswana", "tier": 2, "min_zoom": 3, "orig_lng": 24.471325775}, "geometry": {"type": "Point", "coordinates": [24.471325775, -22.476658800000003]}}, {"type": "Feature", "properties": {"name_zh": "Namibia", "tier": 2, "min_zoom": 3, "orig_lng": 17.928476545454547}, "geometry": {"type": "Point", "coordinates": [17.928476545454547, -21.560888227272727]}}, {"type": "Feature", "properties": {"name_zh": "Senegal", "tier": 3, "min_zoom": 4, "orig_lng": -14.591478727272728}, "geometry": {"type": "Point", "coordinates": [-14.591478727272728, 13.877521909090909]}}, {"type": "Feature", "properties": {"name_zh": "Mali", "tier": 2, "min_zoom": 3, "orig_lng": -5.802088328947368}, "geometry": {"type": "Point", "coordinates": [-5.802088328947368, 14.079544513157893]}}, {"type": "Feature", "properties": {"name_zh": "Mauritania", "tier": 2, "min_zoom": 3, "orig_lng": -12.42493005128205}, "geometry": {"type": "Point", "coordinates": [-12.42493005128205, 18.831379179487183]}}, {"type": "Feature", "properties": {"name_zh": "Benin", "tier": 3, "min_zoom": 4, "orig_lng": 2.32725276}, "geometry": {"type": "Point", "coordinates": [2.32725276, 9.808399960000001]}}, {"type": "Feature", "properties": {"name_zh": "Niger", "tier": 2, "min_zoom": 3, "orig_lng": 8.737445810344827}, "geometry": {"type": "Point", "coordinates": [8.737445810344827, 15.478241672413793]}}, {"type": "Feature", "properties": {"name_zh": "尼日利亚", "tier": 1, "min_zoom": 2, "orig_lng": 8.348453448275862}, "geometry": {"type": "Point", "coordinates": [8.348453448275862, 9.731548293103447]}}, {"type": "Feature", "properties": {"name_zh": "Cameroon", "tier": 2, "min_zoom": 3, "orig_lng": 13.168611672131147}, "geometry": {"type": "Point", "coordinates": [13.168611672131147, 6.906295852459016]}}, {"type": "Feature", "properties": {"name_zh": "Togo", "tier": 3, "min_zoom": 4, "orig_lng": 0.8697444736842105}, "geometry": {"type": "Point", "coordinates": [0.8697444736842105, 8.884753789473683]}}, {"type": "Feature", "properties": {"name_zh": "Ghana", "tier": 3, "min_zoom": 4, "orig_lng": -0.9706184400000001}, "geometry": {"type": "Point", "coordinates": [-0.9706184400000001, 8.29033988]}}, {"type": "Feature", "properties": {"name_zh": "Côte d'Ivoire", "tier": 3, "min_zoom": 4, "orig_lng": -6.345531760869565}, "geometry": {"type": "Point", "coordinates": [-6.345531760869565, 7.94461095652174]}}, {"type": "Feature", "properties": {"name_zh": "Guinea", "tier": 3, "min_zoom": 4, "orig_lng": -10.984555471428573}, "geometry": {"type": "Point", "coordinates": [-10.984555471428573, 10.418830257142858]}}, {"type": "Feature", "properties": {"name_zh": "Guinea-Bissau", "tier": 3, "min_zoom": 4, "orig_lng": -15.213983526315792}, "geometry": {"type": "Point", "coordinates": [-15.213983526315792, 11.979001315789473]}}, {"type": "Feature", "properties": {"name_zh": "Liberia", "tier": 3, "min_zoom": 4, "orig_lng": -9.14270374074074}, "geometry": {"type": "Point", "coordinates": [-9.14270374074074, 6.753908111111111]}}, {"type": "Feature", "properties": {"name_zh": "Sierra Leone", "tier": 3, "min_zoom": 4, "orig_lng": -11.702238772727272}, "geometry": {"type": "Point", "coordinates": [-11.702238772727272, 8.603354681818182]}}, {"type": "Feature", "properties": {"name_zh": "Burkina Faso", "tier": 3, "min_zoom": 4, "orig_lng": -1.916433487179487}, "geometry": {"type": "Point", "coordinates": [-1.916433487179487, 12.111433641025641]}}, {"type": "Feature", "properties": {"name_zh": "Central African Rep.", "tier": 3, "min_zoom": 4, "orig_lng": 20.703062838709677}, "geometry": {"type": "Point", "coordinates": [20.703062838709677, 6.294242322580645]}}, {"type": "Feature", "properties": {"name_zh": "刚果", "tier": 3, "min_zoom": 4, "orig_lng": 14.927109489795917}, "geometry": {"type": "Point", "coordinates": [14.927109489795917, -0.9202092244897959]}}, {"type": "Feature", "properties": {"name_zh": "Gabon", "tier": 3, "min_zoom": 4, "orig_lng": 11.891373580645162}, "geometry": {"type": "Point", "coordinates": [11.891373580645162, -0.337480064516129]}}, {"type": "Feature", "properties": {"name_zh": "Eq. Guinea", "tier": 3, "min_zoom": 4, "orig_lng": 10.069804285714286}, "geometry": {"type": "Point", "coordinates": [10.069804285714286, 1.5893385714285715]}}, {"type": "Feature", "properties": {"name_zh": "Zambia", "tier": 2, "min_zoom": 3, "orig_lng": 27.9779961147541}, "geometry": {"type": "Point", "coordinates": [27.9779961147541, -12.834840639344263]}}, {"type": "Feature", "properties": {"name_zh": "Malawi", "tier": 3, "min_zoom": 4, "orig_lng": 34.062624285714286}, "geometry": {"type": "Point", "coordinates": [34.062624285714286, -12.914038071428573]}}, {"type": "Feature", "properties": {"name_zh": "Mozambique", "tier": 2, "min_zoom": 3, "orig_lng": 35.00352353164557}, "geometry": {"type": "Point", "coordinates": [35.00352353164557, -17.720302240506328]}}, {"type": "Feature", "properties": {"name_zh": "eSwatini", "tier": 3, "min_zoom": 4, "orig_lng": 31.437017818181822}, "geometry": {"type": "Point", "coordinates": [31.437017818181822, -26.42025209090909]}}, {"type": "Feature", "properties": {"name_zh": "Angola", "tier": 2, "min_zoom": 3, "orig_lng": 12.507111777777778}, "geometry": {"type": "Point", "coordinates": [12.507111777777778, -5.039812666666666]}}, {"type": "Feature", "properties": {"name_zh": "Burundi", "tier": 3, "min_zoom": 4, "orig_lng": 30.042267153846158}, "geometry": {"type": "Point", "coordinates": [30.042267153846158, -3.233810153846154]}}, {"type": "Feature", "properties": {"name_zh": "以色列", "tier": 3, "min_zoom": 4, "orig_lng": 35.11451180769231}, "geometry": {"type": "Point", "coordinates": [35.11451180769231, 31.995640076923078]}}, {"type": "Feature", "properties": {"name_zh": "黎巴嫩", "tier": 3, "min_zoom": 4, "orig_lng": 35.85166972727273}, "geometry": {"type": "Point", "coordinates": [35.85166972727273, 33.798193181818185]}}, {"type": "Feature", "properties": {"name_zh": "Madagascar", "tier": 2, "min_zoom": 3, "orig_lng": 46.98921508163266}, "geometry": {"type": "Point", "coordinates": [46.98921508163266, -17.971485102040816]}}, {"type": "Feature", "properties": {"name_zh": "巴勒斯坦", "tier": 3, "min_zoom": 4, "orig_lng": 35.24093522222222}, "geometry": {"type": "Point", "coordinates": [35.24093522222222, 31.80870177777778]}}, {"type": "Feature", "properties": {"name_zh": "Gambia", "tier": 3, "min_zoom": 4, "orig_lng": -15.28718475}, "geometry": {"type": "Point", "coordinates": [-15.28718475, 13.501526125]}}, {"type": "Feature", "properties": {"name_zh": "突尼斯", "tier": 2, "min_zoom": 3, "orig_lng": 9.84151787096774}, "geometry": {"type": "Point", "coordinates": [9.84151787096774, 34.016760322580645]}}, {"type": "Feature", "properties": {"name_zh": "阿尔及利亚", "tier": 1, "min_zoom": 2, "orig_lng": 3.016263887096774}, "geometry": {"type": "Point", "coordinates": [3.016263887096774, 29.665780193548386]}}, {"type": "Feature", "properties": {"name_zh": "约旦", "tier": 3, "min_zoom": 4, "orig_lng": 36.65072505263158}, "geometry": {"type": "Point", "coordinates": [36.65072505263158, 31.132471052631576]}}, {"type": "Feature", "properties": {"name_zh": "United Arab Emirates", "tier": 3, "min_zoom": 4, "orig_lng": 54.243401318181824}, "geometry": {"type": "Point", "coordinates": [54.243401318181824, 24.195379136363638]}}, {"type": "Feature", "properties": {"name_zh": "卡塔尔", "tier": 3, "min_zoom": 4, "orig_lng": 51.151304777777774}, "geometry": {"type": "Point", "coordinates": [51.151304777777774, 25.257109333333332]}}, {"type": "Feature", "properties": {"name_zh": "科威特", "tier": 3, "min_zoom": 4, "orig_lng": 47.742474666666666}, "geometry": {"type": "Point", "coordinates": [47.742474666666666, 29.33678833333333]}}, {"type": "Feature", "properties": {"name_zh": "伊拉克", "tier": 2, "min_zoom": 3, "orig_lng": 44.39874173333333}, "geometry": {"type": "Point", "coordinates": [44.39874173333333, 33.43860503333333]}}, {"type": "Feature", "properties": {"name_zh": "阿曼", "tier": 3, "min_zoom": 4, "orig_lng": 56.56636619512196}, "geometry": {"type": "Point", "coordinates": [56.56636619512196, 20.86002531707317]}}, {"type": "Feature", "properties": {"name_zh": "Vanuatu", "tier": 3, "min_zoom": 4, "orig_lng": 167.3947336}, "geometry": {"type": "Point", "coordinates": [167.3947336, -16.201574]}}, {"type": "Feature", "properties": {"name_zh": "柬埔寨", "tier": 2, "min_zoom": 3, "orig_lng": 104.89517594117648}, "geometry": {"type": "Point", "coordinates": [104.89517594117648, 12.641262529411765]}}, {"type": "Feature", "properties": {"name_zh": "泰国", "tier": 2, "min_zoom": 3, "orig_lng": 100.66150990625}, "geometry": {"type": "Point", "coordinates": [100.66150990625, 13.180763140625]}}, {"type": "Feature", "properties": {"name_zh": "老挝", "tier": 3, "min_zoom": 4, "orig_lng": 103.69295621621622}, "geometry": {"type": "Point", "coordinates": [103.69295621621622, 18.283627675675678]}}, {"type": "Feature", "properties": {"name_zh": "缅甸", "tier": 2, "min_zoom": 3, "orig_lng": 97.15338884285714}, "geometry": {"type": "Point", "coordinates": [97.15338884285714, 20.000520042857143]}}, {"type": "Feature", "properties": {"name_zh": "越南", "tier": 2, "min_zoom": 3, "orig_lng": 105.93873177272727}, "geometry": {"type": "Point", "coordinates": [105.93873177272727, 16.70532434090909]}}, {"type": "Feature", "properties": {"name_zh": "朝鲜", "tier": 2, "min_zoom": 3, "orig_lng": 130.780005}, "geometry": {"type": "Point", "coordinates": [130.780005, 42.22000825]}}, {"type": "Feature", "properties": {"name_zh": "韩国", "tier": 2, "min_zoom": 3, "orig_lng": 127.46743384210525}, "geometry": {"type": "Point", "coordinates": [127.46743384210525, 36.71650668421052]}}, {"type": "Feature", "properties": {"name_zh": "Mongolia", "tier": 1, "min_zoom": 2, "orig_lng": 104.58542652}, "geometry": {"type": "Point", "coordinates": [104.58542652, 47.20451453333333]}}, {"type": "Feature", "properties": {"name_zh": "印度", "tier": 1, "min_zoom": 2, "orig_lng": 83.58820521323528}, "geometry": {"type": "Point", "coordinates": [83.58820521323528, 23.965686544117645]}}, {"type": "Feature", "properties": {"name_zh": "孟加拉国", "tier": 2, "min_zoom": 3, "orig_lng": 90.61132086111111}, "geometry": {"type": "Point", "coordinates": [90.61132086111111, 23.39893386111111]}}, {"type": "Feature", "properties": {"name_zh": "不丹", "tier": 3, "min_zoom": 4, "orig_lng": 90.61513261538462}, "geometry": {"type": "Point", "coordinates": [90.61513261538462, 27.467787]}}, {"type": "Feature", "properties": {"name_zh": "尼泊尔", "tier": 2, "min_zoom": 3, "orig_lng": 84.55865391304349}, "geometry": {"type": "Point", "coordinates": [84.55865391304349, 28.209141304347828]}}, {"type": "Feature", "properties": {"name_zh": "巴基斯坦", "tier": 2, "min_zoom": 3, "orig_lng": 69.44356336363637}, "geometry": {"type": "Point", "coordinates": [69.44356336363637, 30.790385772727273]}}, {"type": "Feature", "properties": {"name_zh": "阿富汗", "tier": 2, "min_zoom": 3, "orig_lng": 67.76801111594203}, "geometry": {"type": "Point", "coordinates": [67.76801111594203, 34.82847544927536]}}, {"type": "Feature", "properties": {"name_zh": "Tajikistan", "tier": 3, "min_zoom": 4, "orig_lng": 70.78717973170733}, "geometry": {"type": "Point", "coordinates": [70.78717973170733, 38.512878585365854]}}, {"type": "Feature", "properties": {"name_zh": "Kyrgyzstan", "tier": 3, "min_zoom": 4, "orig_lng": 73.9767592}, "geometry": {"type": "Point", "coordinates": [73.9767592, 41.3637508]}}, {"type": "Feature", "properties": {"name_zh": "Turkmenistan", "tier": 2, "min_zoom": 3, "orig_lng": 58.456921611111106}, "geometry": {"type": "Point", "coordinates": [58.456921611111106, 39.330051999999995]}}, {"type": "Feature", "properties": {"name_zh": "伊朗", "tier": 1, "min_zoom": 2, "orig_lng": 53.23184946052631}, "geometry": {"type": "Point", "coordinates": [53.23184946052631, 33.35402038157895]}}, {"type": "Feature", "properties": {"name_zh": "叙利亚", "tier": 2, "min_zoom": 3, "orig_lng": 37.95019829629629}, "geometry": {"type": "Point", "coordinates": [37.95019829629629, 35.146206925925924]}}, {"type": "Feature", "properties": {"name_zh": "亚美尼亚", "tier": 3, "min_zoom": 4, "orig_lng": 45.31039225}, "geometry": {"type": "Point", "coordinates": [45.31039225, 39.9454859]}}, {"type": "Feature", "properties": {"name_zh": "瑞典", "tier": 2, "min_zoom": 3, "orig_lng": 16.5632801}, "geometry": {"type": "Point", "coordinates": [16.5632801, 62.73938845]}}, {"type": "Feature", "properties": {"name_zh": "Belarus", "tier": 2, "min_zoom": 3, "orig_lng": 28.30033811111111}, "geometry": {"type": "Point", "coordinates": [28.30033811111111, 53.34756866666667]}}, {"type": "Feature", "properties": {"name_zh": "乌克兰", "tier": 1, "min_zoom": 2, "orig_lng": 30.45089034408602}, "geometry": {"type": "Point", "coordinates": [30.45089034408602, 48.68698113978494]}}, {"type": "Feature", "properties": {"name_zh": "波兰", "tier": 1, "min_zoom": 2, "orig_lng": 19.475697044444445}, "geometry": {"type": "Point", "coordinates": [19.475697044444445, 51.74479997777778]}}, {"type": "Feature", "properties": {"name_zh": "奥地利", "tier": 3, "min_zoom": 4, "orig_lng": 13.48457318918919}, "geometry": {"type": "Point", "coordinates": [13.48457318918919, 47.64469881081081]}}, {"type": "Feature", "properties": {"name_zh": "Hungary", "tier": 3, "min_zoom": 4, "orig_lng": 19.23192871875}, "geometry": {"type": "Point", "coordinates": [19.23192871875, 47.4161563125]}}, {"type": "Feature", "properties": {"name_zh": "Moldova", "tier": 3, "min_zoom": 4, "orig_lng": 28.47035211111111}, "geometry": {"type": "Point", "coordinates": [28.47035211111111, 47.04663955555556]}}, {"type": "Feature", "properties": {"name_zh": "Romania", "tier": 2, "min_zoom": 3, "orig_lng": 25.18828361363636}, "geometry": {"type": "Point", "coordinates": [25.18828361363636, 45.856761931818184]}}, {"type": "Feature", "properties": {"name_zh": "Lithuania", "tier": 3, "min_zoom": 4, "orig_lng": 24.016552684210527}, "geometry": {"type": "Point", "coordinates": [24.016552684210527, 55.20095163157894]}}, {"type": "Feature", "properties": {"name_zh": "Latvia", "tier": 3, "min_zoom": 4, "orig_lng": 24.940212136363638}, "geometry": {"type": "Point", "coordinates": [24.940212136363638, 56.857665545454545]}}, {"type": "Feature", "properties": {"name_zh": "Estonia", "tier": 3, "min_zoom": 4, "orig_lng": 26.14205405263158}, "geometry": {"type": "Point", "coordinates": [26.14205405263158, 58.69707121052632]}}, {"type": "Feature", "properties": {"name_zh": "德国", "tier": 1, "min_zoom": 2, "orig_lng": 10.69112601724138}, "geometry": {"type": "Point", "coordinates": [10.69112601724138, 51.04436703448276]}}, {"type": "Feature", "properties": {"name_zh": "Bulgaria", "tier": 3, "min_zoom": 4, "orig_lng": 24.687321107142857}, "geometry": {"type": "Point", "coordinates": [24.687321107142857, 42.893661214285714]}}, {"type": "Feature", "properties": {"name_zh": "希腊", "tier": 2, "min_zoom": 3, "orig_lng": 25.10962381818182}, "geometry": {"type": "Point", "coordinates": [25.10962381818182, 35.26563490909091]}}, {"type": "Feature", "properties": {"name_zh": "土耳其", "tier": 1, "min_zoom": 2, "orig_lng": 36.90125642592592}, "geometry": {"type": "Point", "coordinates": [36.90125642592592, 38.37814322222222]}}, {"type": "Feature", "properties": {"name_zh": "Albania", "tier": 3, "min_zoom": 4, "orig_lng": 20.116781083333333}, "geometry": {"type": "Point", "coordinates": [20.116781083333333, 41.28046204166667]}}, {"type": "Feature", "properties": {"name_zh": "Croatia", "tier": 3, "min_zoom": 4, "orig_lng": 16.431294511627907}, "geometry": {"type": "Point", "coordinates": [16.431294511627907, 44.84539930232558]}}, {"type": "Feature", "properties": {"name_zh": "瑞士", "tier": 3, "min_zoom": 4, "orig_lng": 8.306507541666667}, "geometry": {"type": "Point", "coordinates": [8.306507541666667, 46.79685429166667]}}, {"type": "Feature", "properties": {"name_zh": "Luxembourg", "tier": 3, "min_zoom": 4, "orig_lng": 5.981349285714286}, "geometry": {"type": "Point", "coordinates": [5.981349285714286, 49.81208742857143]}}, {"type": "Feature", "properties": {"name_zh": "比利时", "tier": 3, "min_zoom": 4, "orig_lng": 4.432619117647058}, "geometry": {"type": "Point", "coordinates": [4.432619117647058, 50.715869352941176]}}, {"type": "Feature", "properties": {"name_zh": "荷兰", "tier": 3, "min_zoom": 4, "orig_lng": 5.489893666666666}, "geometry": {"type": "Point", "coordinates": [5.489893666666666, 52.10253546666667]}}, {"type": "Feature", "properties": {"name_zh": "葡萄牙", "tier": 3, "min_zoom": 4, "orig_lng": -8.038668363636363}, "geometry": {"type": "Point", "coordinates": [-8.038668363636363, 39.764078545454545]}}, {"type": "Feature", "properties": {"name_zh": "西班牙", "tier": 1, "min_zoom": 2, "orig_lng": -4.450721470588236}, "geometry": {"type": "Point", "coordinates": [-4.450721470588236, 40.17528431372549]}}, {"type": "Feature", "properties": {"name_zh": "Ireland", "tier": 3, "min_zoom": 4, "orig_lng": -7.723323615384615}, "geometry": {"type": "Point", "coordinates": [-7.723323615384615, 53.53152307692308]}}, {"type": "Feature", "properties": {"name_zh": "New Caledonia", "tier": 3, "min_zoom": 4, "orig_lng": 165.51165784615384}, "geometry": {"type": "Point", "coordinates": [165.51165784615384, -21.177657615384614]}}, {"type": "Feature", "properties": {"name_zh": "Solomon Is.", "tier": 3, "min_zoom": 4, "orig_lng": 161.92898466666665}, "geometry": {"type": "Point", "coordinates": [161.92898466666665, -10.543878]}}, {"type": "Feature", "properties": {"name_zh": "新西兰", "tier": 2, "min_zoom": 3, "orig_lng": 175.48133422222224}, "geometry": {"type": "Point", "coordinates": [175.48133422222224, -38.19715138888889]}}, {"type": "Feature", "properties": {"name_zh": "澳大利亚", "tier": 1, "min_zoom": 2, "orig_lng": 146.70382029411766}, "geometry": {"type": "Point", "coordinates": [146.70382029411766, -41.964737235294116]}}, {"type": "Feature", "properties": {"name_zh": "斯里兰卡", "tier": 3, "min_zoom": 4, "orig_lng": 80.8638191}, "geometry": {"type": "Point", "coordinates": [80.8638191, 7.6314413000000005]}}, {"type": "Feature", "properties": {"name_zh": "中国", "tier": 1, "min_zoom": 2, "orig_lng": 109.8268937}, "geometry": {"type": "Point", "coordinates": [109.8268937, 19.1901003]}}, {"type": "Feature", "properties": {"name_zh": "台湾", "tier": 3, "min_zoom": 4, "orig_lng": 121.10506533333334}, "geometry": {"type": "Point", "coordinates": [121.10506533333334, 23.86140066666667]}}, {"type": "Feature", "properties": {"name_zh": "意大利", "tier": 1, "min_zoom": 2, "orig_lng": 12.62657565151515}, "geometry": {"type": "Point", "coordinates": [12.62657565151515, 43.08665778787879]}}, {"type": "Feature", "properties": {"name_zh": "丹麦", "tier": 3, "min_zoom": 4, "orig_lng": 9.622694166666667}, "geometry": {"type": "Point", "coordinates": [9.622694166666667, 56.2779605]}}, {"type": "Feature", "properties": {"name_zh": "英国", "tier": 1, "min_zoom": 2, "orig_lng": -6.781957875}, "geometry": {"type": "Point", "coordinates": [-6.781957875, 54.41546425]}}, {"type": "Feature", "properties": {"name_zh": "冰岛", "tier": 3, "min_zoom": 4, "orig_lng": -19.2659774}, "geometry": {"type": "Point", "coordinates": [-19.2659774, 65.27802870000001]}}, {"type": "Feature", "properties": {"name_zh": "Azerbaijan", "tier": 3, "min_zoom": 4, "orig_lng": 47.40568257142857}, "geometry": {"type": "Point", "coordinates": [47.40568257142857, 40.373409]}}, {"type": "Feature", "properties": {"name_zh": "格鲁吉亚", "tier": 3, "min_zoom": 4, "orig_lng": 43.36364137499999}, "geometry": {"type": "Point", "coordinates": [43.36364137499999, 42.258454291666666]}}, {"type": "Feature", "properties": {"name_zh": "菲律宾", "tier": 2, "min_zoom": 3, "orig_lng": 120.99349}, "geometry": {"type": "Point", "coordinates": [120.99349, 12.930042]}}, {"type": "Feature", "properties": {"name_zh": "马来西亚", "tier": 2, "min_zoom": 3, "orig_lng": 102.07510724}, "geometry": {"type": "Point", "coordinates": [102.07510724, 4.35256256]}}, {"type": "Feature", "properties": {"name_zh": "Brunei", "tier": 3, "min_zoom": 4, "orig_lng": 114.998464}, "geometry": {"type": "Point", "coordinates": [114.998464, 4.743645]}}, {"type": "Feature", "properties": {"name_zh": "Slovenia", "tier": 3, "min_zoom": 4, "orig_lng": 14.99537788888889}, "geometry": {"type": "Point", "coordinates": [14.99537788888889, 46.10708266666667]}}, {"type": "Feature", "properties": {"name_zh": "芬兰", "tier": 2, "min_zoom": 3, "orig_lng": 25.886752050000002}, "geometry": {"type": "Point", "coordinates": [25.886752050000002, 65.228398075]}}, {"type": "Feature", "properties": {"name_zh": "斯洛伐克", "tier": 3, "min_zoom": 4, "orig_lng": 19.351837454545453}, "geometry": {"type": "Point", "coordinates": [19.351837454545453, 48.76384075757576]}}, {"type": "Feature", "properties": {"name_zh": "捷克", "tier": 3, "min_zoom": 4, "orig_lng": 15.848031200000001}, "geometry": {"type": "Point", "coordinates": [15.848031200000001, 49.77865917142857]}}, {"type": "Feature", "properties": {"name_zh": "Eritrea", "tier": 3, "min_zoom": 4, "orig_lng": 39.588338178571426}, "geometry": {"type": "Point", "coordinates": [39.588338178571426, 14.712020642857143]}}, {"type": "Feature", "properties": {"name_zh": "日本", "tier": 1, "min_zoom": 2, "orig_lng": 135.99567897297297}, "geometry": {"type": "Point", "coordinates": [135.99567897297297, 35.72025940540541]}}, {"type": "Feature", "properties": {"name_zh": "Paraguay", "tier": 2, "min_zoom": 3, "orig_lng": -57.56991790909091}, "geometry": {"type": "Point", "coordinates": [-57.56991790909091, -23.30197578787879]}}, {"type": "Feature", "properties": {"name_zh": "也门", "tier": 2, "min_zoom": 3, "orig_lng": 46.47150418181818}, "geometry": {"type": "Point", "coordinates": [46.47150418181818, 15.511892840909091]}}, {"type": "Feature", "properties": {"name_zh": "沙特阿拉伯", "tier": 1, "min_zoom": 2, "orig_lng": 43.59399496052632}, "geometry": {"type": "Point", "coordinates": [43.59399496052632, 24.040204026315788]}}, {"type": "Feature", "properties": {"name_zh": "Antarctica", "tier": 3, "min_zoom": 4, "orig_lng": -48.35258927272727}, "geometry": {"type": "Point", "coordinates": [-48.35258927272727, -79.35454045454546]}}, {"type": "Feature", "properties": {"name_zh": "N. Cyprus", "tier": 3, "min_zoom": 4, "orig_lng": 33.4265471875}, "geometry": {"type": "Point", "coordinates": [33.4265471875, 35.177307375]}}, {"type": "Feature", "properties": {"name_zh": "Cyprus", "tier": 3, "min_zoom": 4, "orig_lng": 33.24416573333333}, "geometry": {"type": "Point", "coordinates": [33.24416573333333, 35.024599800000004]}}, {"type": "Feature", "properties": {"name_zh": "摩洛哥", "tier": 2, "min_zoom": 3, "orig_lng": -9.42593634920635}, "geometry": {"type": "Point", "coordinates": [-9.42593634920635, 28.769843365079367]}}, {"type": "Feature", "properties": {"name_zh": "埃及", "tier": 1, "min_zoom": 2, "orig_lng": 31.69790109090909}, "geometry": {"type": "Point", "coordinates": [31.69790109090909, 28.17505597727273]}}, {"type": "Feature", "properties": {"name_zh": "利比亚", "tier": 1, "min_zoom": 2, "orig_lng": 16.638207714285716}, "geometry": {"type": "Point", "coordinates": [16.638207714285716, 28.476834160714283]}}, {"type": "Feature", "properties": {"name_zh": "埃塞俄比亚", "tier": 2, "min_zoom": 3, "orig_lng": 39.20915761016949}, "geometry": {"type": "Point", "coordinates": [39.20915761016949, 8.983416983050848]}}, {"type": "Feature", "properties": {"name_zh": "Djibouti", "tier": 3, "min_zoom": 4, "orig_lng": 42.52214946666666}, "geometry": {"type": "Point", "coordinates": [42.52214946666666, 11.800378733333334]}}, {"type": "Feature", "properties": {"name_zh": "Somaliland", "tier": 3, "min_zoom": 4, "orig_lng": 46.35218169230769}, "geometry": {"type": "Point", "coordinates": [46.35218169230769, 10.47035746153846]}}, {"type": "Feature", "properties": {"name_zh": "Uganda", "tier": 3, "min_zoom": 4, "orig_lng": 31.95123182142857}, "geometry": {"type": "Point", "coordinates": [31.95123182142857, 1.3389631785714287]}}, {"type": "Feature", "properties": {"name_zh": "Rwanda", "tier": 3, "min_zoom": 4, "orig_lng": 29.929474642857144}, "geometry": {"type": "Point", "coordinates": [29.929474642857144, -2.0071987142857144]}}, {"type": "Feature", "properties": {"name_zh": "Bosnia and Herz.", "tier": 3, "min_zoom": 4, "orig_lng": 17.92135656521739}, "geometry": {"type": "Point", "coordinates": [17.92135656521739, 44.185040173913045]}}, {"type": "Feature", "properties": {"name_zh": "North Macedonia", "tier": 3, "min_zoom": 4, "orig_lng": 21.6265665}, "geometry": {"type": "Point", "coordinates": [21.6265665, 41.683540444444446]}}, {"type": "Feature", "properties": {"name_zh": "Serbia", "tier": 3, "min_zoom": 4, "orig_lng": 20.855446520833333}, "geometry": {"type": "Point", "coordinates": [20.855446520833333, 43.89467185416667]}}, {"type": "Feature", "properties": {"name_zh": "Montenegro", "tier": 3, "min_zoom": 4, "orig_lng": 19.446579166666666}, "geometry": {"type": "Point", "coordinates": [19.446579166666666, 42.741404333333335]}}, {"type": "Feature", "properties": {"name_zh": "Kosovo", "tier": 3, "min_zoom": 4, "orig_lng": 20.957034285714286}, "geometry": {"type": "Point", "coordinates": [20.957034285714286, 42.54599414285714]}}, {"type": "Feature", "properties": {"name_zh": "Trinidad and Tobago", "tier": 3, "min_zoom": 4, "orig_lng": -61.459375}, "geometry": {"type": "Point", "coordinates": [-61.459375, 10.47875]}}, {"type": "Feature", "properties": {"name_zh": "S. Sudan", "tier": 3, "min_zoom": 4, "orig_lng": 30.092555126984127}, "geometry": {"type": "Point", "coordinates": [30.092555126984127, 8.009772507936509]}}]}